mis_scan_handler/__init__.py
mis_scan_handler/__main__.py
mis_scan_handler/_version.py
mis_scan_handler/main.py
mis_scan_handler/handlers/__init__.py
mis_scan_handler/handlers/atf.py
mis_scan_handler/handlers/database.py
mis_scan_handler/handlers/sql.py
mis_scan_handler-1.0.0rc2.dist-info/METADATA
mis_scan_handler-1.0.0rc2.dist-info/WHEEL
mis_scan_handler-1.0.0rc2.dist-info/entry_points.txt
mis_scan_handler-1.0.0rc2.dist-info/top_level.txt
mis_scan_handler-1.0.0rc2.dist-info/RECORD
