Metadata-Version: 2.1
Name: mis-scan-handler
Version: 1.0.0rc2
Summary: Processing scans of machine-readable TrustMed documents
Home-page: https://github.com/mnogomed/mis-scan-handler
Author: Chmelyuk Vladislav
Author-email: neimp@yandex.ru
License: UNKNOWN
Platform: UNKNOWN
Classifier: License :: OSI Approved :: MIT License
Classifier: Natural Language :: Russian
Classifier: Operating System :: OS Independent
Classifier: Programming Language :: Python
Classifier: Programming Language :: Python :: 3
Classifier: Programming Language :: Python :: 3 :: Only
Classifier: Programming Language :: Python :: 3.7
Classifier: Programming Language :: Python :: 3.8
Classifier: Programming Language :: Python :: 3.9
Classifier: Programming Language :: Python :: 3.10
Classifier: Topic :: Utilities
Requires-Dist: typer (~=0.4)
Requires-Dist: pymssql (~=2.2)
Requires-Dist: pdf2image (~=1.16)
Requires-Dist: pyzbar (~=0.1)
Requires-Dist: loguru (~=0.5)
Requires-Dist: Pillow (~=8.3)
Requires-Dist: numpy (~=1.19)
Requires-Dist: opencv-python (~=4.5.3)
